phl_courts_scraper/__init__.py
phl_courts_scraper/base.py
phl_courts_scraper/court_summary/__init__.py
phl_courts_scraper/court_summary/core.py
phl_courts_scraper/court_summary/schema.py
phl_courts_scraper/docket_sheet/__init__.py
phl_courts_scraper/docket_sheet/core.py
phl_courts_scraper/docket_sheet/schema.py
phl_courts_scraper/portal/__init__.py
phl_courts_scraper/portal/core.py
phl_courts_scraper/portal/schema.py
phl_courts_scraper/utils.py
phl_courts_scraper-0.1.1.dist-info/LICENSE
phl_courts_scraper-0.1.1.dist-info/WHEEL
phl_courts_scraper-0.1.1.dist-info/METADATA
phl_courts_scraper-0.1.1.dist-info/RECORD
