Metadata-Version: 2.1
Name: phl-courts-scraper
Version: 0.1.1
Summary: A Python utility to scrape docket sheets and court summaries for Philadelphia courts.
License: MIT
Author: Nick Hand
Author-email: nick.hand@phila.gov
Requires-Python: >=3.7.1,<4.0.0
Classifier: License :: OSI Approved :: MIT License
Classifier: Programming Language :: Python :: 3
Classifier: Programming Language :: Python :: 3.10
Classifier: Programming Language :: Python :: 3.8
Classifier: Programming Language :: Python :: 3.9
Requires-Dist: beautifulsoup4 (>=4.10.0,<5.0.0)
Requires-Dist: desert (>=2020.11.18,<2021.0.0)
Requires-Dist: importlib-metadata (>=4.8.1,<5.0.0)
Requires-Dist: intervaltree (>=3.1.0,<4.0.0)
Requires-Dist: loguru (>=0.5.3,<0.6.0)
Requires-Dist: pandas (>=1.3.3,<2.0.0)
Requires-Dist: pdfplumber (>=0.5.28,<0.6.0)
Requires-Dist: selenium (>=4.0.0,<5.0.0)
Requires-Dist: tryagain (>=1.0,<2.0)
Requires-Dist: webdriver-manager (>=3.5.0,<4.0.0)
